{
    "main": {
        "mimetype": "image/jpeg", 
        "conenttype": "Image", 
        "id": 1821386508, 
        "stati": [
            "visible.default", 
            "modify.default"
        ]
    }, 
    "dublin": {
        "rights": "", 
        "publisher": "", 
        "identifier": "", 
        "description": "", 
        "contributors": [], 
        "title": "file_mcompanyinfo_08.jpg", 
        "created": "2009-01-18 04:41:14", 
        "modified": "2009-01-18 04:41:14", 
        "language": "", 
        "subjects": [], 
        "creators": [
            "users.anson"
        ], 
        "type": ""
    }
}